CHANGES.txt
MANIFEST.in
README.txt
setup.cfg
setup.py
src/test.py
src/erp5.appliance.test.egg-info/PKG-INFO
src/erp5.appliance.test.egg-info/SOURCES.txt
src/erp5.appliance.test.egg-info/dependency_links.txt
src/erp5.appliance.test.egg-info/entry_points.txt
src/erp5.appliance.test.egg-info/requires.txt
src/erp5.appliance.test.egg-info/top_level.txt