Metadata-Version: 1.0
Name: erp5.appliance.test
Version: 2.10
Summary: ERP5 Appliance testing system
Home-page: http://svn.erp5.org/erp5/trunk/utils/erp5.appliance.test
Author: Lukasz Nowak
Author-email: luke@nexedi.com
License: GPL
Keywords: erp5 appliance test
Platform: UNKNOWN
Classifier: Environment :: Console
Classifier: Intended Audience :: Developers
Classifier: License :: OSI Approved :: GNU General Public License (GPL)
Classifier: Operating System :: POSIX
Classifier: Topic :: Software Development :: Testing
Classifier: Programming Language :: Python :: 2.4
Classifier: Programming Language :: Python :: 2.5
Classifier: Programming Language :: Python :: 2.6
Classifier: Programming Language :: Python :: 2.7
